[
  {
    "title": "アメリカと日本が、お金の約束をしたよ！",
    "content": "アメリカの偉い人が、日本と仲良くすることにしたんだって。日本がアメリカにお金をたくさん投資する代わりに、アメリカは日本から物が入ってくるときの税金を安くするんだって。特に車にかかる税金が安くなるみたいだよ！ 詳しくはまだこれからわかるみたい。"
  },
  {
    "title": "日本とアメリカ、仲良く税金を安くすることにした！",
    "content": "日本の偉い人が、アメリカとの税金についての約束ができたって言ったよ。アメリカが日本から車を買うときにかかる税金が安くなるんだって！ 日本とアメリカ、両方にとって良いことになったって言ってるよ！"
  },
  {
    "title": "日本、アメリカのお米をたくさん買うことにした！",
    "content": "日本は毎年、外国からお米を決められた量だけ買っているんだ。今回、アメリカとの約束で、その中でアメリカのお米を今までより多く買うことになったんだって！ でも、外国から買うお米の量は変わらないんだって。"
  },
  {
    "title": "株価がグーンと上がった！ 日本とアメリカの仲良しのおかげ！",
    "content": "日本とアメリカが仲良く税金のことを決めたから、東京の株っていう値段がいっぱい上がったんだって！ 特に車を作る会社とか、外国に物を売る会社がもっと頑張れるかもって思って、みんなが株を買ったからなんだって！"
  },
  {
    "title": "石破総理大臣、まだ辞めないみたい！",
    "content": "石破総理大臣が、もうちょっと総理大臣を続けたいって言ったんだ。でも、自民党の中の若い人たちや地方の人たちからは「辞めてほしい」って声がたくさん出てるんだって。石破総理大臣は、昔総理大臣だった人たちに会って、これからどうするか相談するみたいだよ。みんなに協力してもらえるように頑張るみたい！"
  },
  {
    "title": "北海道の東の方、今日とっても暑くなるから気をつけて！",
    "content": "今日は日本全国で暑いけど、特に北海道の東のほうは、命に関わるくらいとっても暑くなるかもしれないんだって！ 熱中症にならないように、こまめに水分をとって、無理しないでね！"
  },
  {
    "title": "台風が来るぞ！ 沖縄のお友達は気をつけて！",
    "content": "台風7号っていうのができたんだって！ 明日か明後日に沖縄に近づくみたいだから、沖縄のお友達は大雨とか高い波に気をつけてね！ 天気予報をよく見て、危ないところには行かないようにしよう！"
  }
]